ilupp/__init__.py
ilupp/_ilupp.cp37-win_amd64.pyd
ilupp-1.0.2.dist-info/LICENSE
ilupp-1.0.2.dist-info/METADATA
ilupp-1.0.2.dist-info/WHEEL
ilupp-1.0.2.dist-info/top_level.txt
ilupp-1.0.2.dist-info/RECORD
