Metadata-Version: 2.0
Name: ilupp
Version: 1.0.2
Summary: Incomplete LU algorithms for C++ and Python
Home-page: https://github.com/c-f-h/ilupp
Author: Clemens Hofreither
Author-email: chofreither@gmail.com
License: UNKNOWN
Platform: UNKNOWN
Classifier: Programming Language :: Python :: 2.7
Classifier: Programming Language :: Python :: 3
Classifier: Intended Audience :: Science/Research
Classifier: Topic :: Scientific/Engineering :: Mathematics
Classifier: License :: OSI Approved :: GNU General Public License v3 or later (GPLv3+)
Requires-Dist: numpy (>=1.11)
Requires-Dist: scipy
